{"chunk_definitions":[{"row":221,"row_count":1,"visible":true,"expansion_state":0,"options":{"engine":"r","label":"unnamed-chunk-18","echo":true,"message":false,"warning":false,"paged.print":false,"dev":"png"},"document_id":"B499FCE6","chunk_id":"cwzq3wdw9b43y","chunk_label":"unnamed-chunk-1"},{"row":329,"row_count":1,"visible":true,"expansion_state":0,"options":{"engine":"r","label":"unnamed-chunk-21","message":false,"warning":false,"paged.print":false,"dev":"png"},"document_id":"B499FCE6","chunk_id":"cuibk24rqqesv","chunk_label":"unnamed-chunk-2"}],"doc_write_time":1747973264}